dqlauncher/__init__.py
dqlauncher/session.py
dqlauncher/utilities/__init__.py
dqlauncher/utilities/errors.py
dqlauncher/utilities/functions.py
dqlauncher/validator.py
dqlauncher-1.0.dist-info/LICENSE.md
dqlauncher-1.0.dist-info/METADATA
dqlauncher-1.0.dist-info/WHEEL
dqlauncher-1.0.dist-info/RECORD
