Metadata-Version: 2.1
Name: dqlauncher
Version: 1.0
Summary: DataQuality functions over pyspark.sql SparkSession and DataFrame
Home-page: https://github.com/sierrapablo/DQ-Launcher
License: MIT
Author: Pablo Sierra Lorente
Author-email: pablosierralorente@outlook.es
Requires-Python: >=3.11,<4.0
Classifier: Development Status :: 3 - Alpha
Classifier: Intended Audience :: Developers
Classifier: License :: OSI Approved :: MIT License
Classifier: Programming Language :: Python :: 3
Classifier: Programming Language :: Python :: 3.11
Classifier: Topic :: Software Development :: Libraries :: Python Modules
Requires-Dist: numpy (==1.26.1)
Requires-Dist: pandas (==2.1.1)
Requires-Dist: py4j (==0.10.9.7)
Requires-Dist: pyspark (==3.5.0)
Requires-Dist: python-dateutil (>=2.8.2)
Requires-Dist: pytz (>=2023.3.post1)
Requires-Dist: six (>=1.16.0)
Requires-Dist: tzdata (>=2023.3)
